Workbook

Sheet Inputs
A1: Projeto 2 — Inventory & Profit Optimization | Inputs
A3: Categoria | B3: Demanda prevista (8 semanas) | C3: Preço efetivo (R$/un.) | D3: Custo unitário (R$/un.) | E3: Lucro unitário (R$/un.) | F3: Fonte / Observação
A4: Electronics | B4: 1807 | C4: 1284 | D4: 834.6 | E4: =C4-D4 -> 449.4 | F4: Projeto 1 — cenário Base; custo = 65% do preço-base
A5: Personal Care | B5: 2671 | C5: 1670.5 | D5: 918.775 | E5: =C5-D5 -> 751.725 | F5: Projeto 1 — cenário Base; custo = 55% do preço-base
A8: Premissas operacionais do Solver
A9: Premissa | B9: Valor | C9: Unidade | D9: Observação
A10: Orçamento disponível | B10: 1500000 | C10: R$ | D10: Limite máximo de investimento em estoque
A11: Capacidade total | B11: 4000 | C11: unidades | D11: Limite máximo de unidades compradas
A12: Compra mínima por categoria | B12: 0.2 | C12: % da demanda | D12: Garante presença mínima das duas categorias
A13: Horizonte | B13: 8 | C13: semanas | D13: Mesmo horizonte do forecast do Projeto 1
A14: Quantidades inteiras | B14: 1 | C14: sim/não | D14: 1 = exigir números inteiros no Solver
A16: Nota metodológica
A17: Os dados de demanda, preço e custo vêm do cenário-base do Projeto 1. Os custos são premissas explícitas porque a base original não continha custo real do produto.
A18: Objetivo do Projeto 2: alocar um orçamento limitado entre as categorias para maximizar o lucro esperado, respeitando demanda prevista e restrições operacionais.

Sheet Solver_Model
A1: Projeto 2 — Modelo de Otimização com Solver
A3: Categoria | B3: Demanda prevista | C3: Compra mínima | D3: Qtd. a comprar | E3: Preço efetivo | F3: Custo unitário | G3: Lucro unitário | H3: Investimento | I3: Receita | J3: Lucro esperado
A4: Electronics | B4: =Inputs!B4 -> 1807 | C4: =B4*Inputs!$B$12 -> 361.4 | D4: 361.4 | E4: =Inputs!C4 -> 1284 | F4: =Inputs!D4 -> 834.6 | G4: =Inputs!E4 -> 449.4 | H4: =D4*F4 -> 301624.44 | I4: =D4*E4 -> 464037.6 | J4: =D4*G4 -> 162413.16
A5: Personal Care | B5: =Inputs!B5 -> 2671 | C5: =B5*Inputs!$B$12 -> 534.2 | D5: 1304.3189 | E5: =Inputs!C5 -> 1670.5 | F5: =Inputs!D5 -> 918.775 | G5: =Inputs!E5 -> 751.725 | H5: =D5*F5 -> 1198375.6 | I5: =D5*E5 -> 2178864.7 | J5: =D5*G5 -> 980489.09
A7: TOTAL | D7: =SUM(D4:D5) -> 1665.7189 | H7: =SUM(H4:H5) -> 1500000 | I7: =SUM(I4:I5) -> 2642902.3 | J7: =SUM(J4:J5) -> 1142902.3
A10: Painel de restrições
A11: Restrição | B11: Usado | C11: Limite | D11: Folga
A12: Orçamento | B12: =H7 -> 1500000 | C12: =Inputs!B10 -> 1500000 | D12: =C12-B12 -> -8.7544322e-08
A13: Capacidade total | B13: =D7 -> 1665.7189 | C13: =Inputs!B11 -> 4000 | D13: =C13-B13 -> 2334.2811
A14: Mínimo Electronics | B14: =D4 -> 361.4 | C14: =C4 -> 361.4 | D14: =B14-C14 -> 0
A15: Mínimo Personal Care | B15: =D5 -> 1304.3189 | C15: =C5 -> 534.2 | D15: =B15-C15 -> 770.11886
A18: Função objetivo
A19: Objetivo | B19: Maximizar Lucro Total
A20: Célula objetivo | B20: J7
A21: Células variáveis | B21: D4:D5

Sheet Como_Usar
A1: Como configurar o Solver no Excel — passo a passo
A3: Passo | B3: Ação | C3: Configuração | D3: Por quê | E3: Células | F3: Resultado esperado
A4: 1 | B4: Ativar o Solver | C4: Arquivo > Opções > Suplementos > Gerenciar Suplementos do Excel > Ir > marcar Solver | D4: Habilita a ferramenta de otimização | E4: - | F4: Solver aparece na guia Dados
A5: 2 | B5: Abrir o Solver | C5: Dados > Solver | D5: Abre o painel de otimização | E5: - | F5: Janela Parâmetros do Solver
A6: 3 | B6: Definir objetivo | C6: Definir Objetivo = $J$7 | D6: J7 soma o lucro esperado das duas categorias | E6: Solver_Model!J7 | F6: Maximizar lucro total
A7: 4 | B7: Escolher direção | C7: Selecionar Máx | D7: Queremos o maior lucro possível | E7: - | F7: Objetivo configurado como maximização
A8: 5 | B8: Definir variáveis | C8: Alterando Células Variáveis = $D$4:$D$5 | D8: São as quantidades a comprar | E8: Solver_Model!D4:D5 | F8: Solver pode alterar as compras
A9: 6 | B9: Adicionar restrição | C9: $H$7 <= Inputs!$B$10 | D9: Investimento total não pode superar R$ 1,5 milhão | E9: H7 e Inputs!B10 | F9: Respeita orçamento
A10: 7 | B10: Adicionar restrição | C10: $D$7 <= Inputs!$B$11 | D10: Total comprado não pode superar 4.000 unidades | E10: D7 e Inputs!B11 | F10: Respeita capacidade
A11: 8 | B11: Adicionar restrição | C11: $D$4:$D$5 <= $B$4:$B$5 | D11: Não comprar mais que a demanda prevista | E11: D4:D5 e B4:B5 | F11: Evita excesso sobre forecast
A12: 9 | B12: Adicionar restrição | C12: $D$4:$D$5 >= $C$4:$C$5 | D12: Compra mínima de 20% da demanda | E12: D4:D5 e C4:C5 | F12: Mantém presença mínima
A13: 10 | B13: Adicionar restrição | C13: $D$4:$D$5 = inteiro | D13: Não existem frações de unidade | E13: D4:D5 | F13: Quantidades inteiras
A14: 11 | B14: Método | C14: Selecionar Simplex LP | D14: O problema é linear | E14: - | F14: Solução eficiente e reproduzível
A15: 12 | B15: Resolver | C15: Clique em Resolver e mantenha a solução do Solver | D15: Executa a otimização | E15: - | F15: D4:D5 passam a mostrar a alocação ótima
A18: Como interpretar o resultado
A19: 1 | B19: Observe D4 e D5 | C19: São as quantidades ótimas de compra
A20: 2 | B20: Observe H7 | C20: É o capital usado pelo Solver
A21: 3 | B21: Observe J7 | C21: É o maior lucro encontrado sob as restrições
A22: 4 | B22: Observe D12:D15 | C22: Folgas negativas significam restrição violada; após Solver devem estar >= 0
A23: 5 | B23: Compare com uma alocação manual | C23: O valor do Solver mostra quanto lucro se ganha com uma decisão otimizada
